nolds/__init__.py
nolds/datasets.py
nolds/examples.py
nolds/measures.py
nolds/test_measures.py
nolds/datasets/^JKSE.csv
nolds/datasets/^N225.csv
nolds/datasets/^NDX.csv
nolds/datasets/brown72.npy
nolds/datasets/qrandom.npy
nolds-0.6.0.dist-info/LICENSE.txt
nolds-0.6.0.dist-info/METADATA
nolds-0.6.0.dist-info/WHEEL
nolds-0.6.0.dist-info/top_level.txt
nolds-0.6.0.dist-info/RECORD
