Metadata-Version: 2.1
Name: nolds
Version: 0.6.0
Summary: Nonlinear measures for dynamical systems (based on one-dimensional time series)
Home-page: https://github.com/CSchoel/nolds
Download-URL: https://github.com/CSchoel/nolds/tarball/0.6.0
Author: Christopher Schölzel
Author-email: christopher.schoelzel@gmx.net
License: MIT
Keywords: nonlinear,dynamical system,chaos,lyapunov,hurst,hurst exponent,rescaled range,DFA,detrended fluctuation analysis,sample entropy,correlation dimension
Platform: any
Classifier: Development Status :: 4 - Beta
Classifier: Intended Audience :: Education
Classifier: Intended Audience :: Science/Research
Classifier: License :: OSI Approved :: MIT License
Classifier: Topic :: Scientific/Engineering :: Bio-Informatics
Classifier: Programming Language :: Python :: 2
Classifier: Programming Language :: Python :: 2.7
Classifier: Programming Language :: Python :: 3
Classifier: Programming Language :: Python :: 3.4
Classifier: Programming Language :: Python :: 3.5
Classifier: Programming Language :: Python :: 3.6
Classifier: Programming Language :: Python :: 3.7
License-File: LICENSE.txt
Requires-Dist: numpy <2.0
Requires-Dist: future
Requires-Dist: setuptools
Provides-Extra: ransac
Requires-Dist: sklearn >=0.19 ; extra == 'ransac'
Provides-Extra: plots
Requires-Dist: matplotlib ; extra == 'plots'
Provides-Extra: qrandom
Requires-Dist: quantumrandom ; extra == 'qrandom'
